sfe/Cal_Comb.py
sfe/Element.py
sfe/Element_Type.py
sfe/Node.py
sfe/__init__.py
sfe/figure.py
sfe/setup.py
sfe/solve.py
sfe/sfe/Cal_Comb.py
sfe/sfe/Element.py
sfe/sfe/Element_Type.py
sfe/sfe/Node.py
sfe/sfe/__init__.py
sfe/sfe/figure.py
sfe/sfe/solve.py
cs20220112-0.2.dist-info/LICENSE.txt
cs20220112-0.2.dist-info/METADATA
cs20220112-0.2.dist-info/WHEEL
cs20220112-0.2.dist-info/top_level.txt
cs20220112-0.2.dist-info/RECORD
