Metadata-Version: 2.1
Name: cs20220112
Version: 0.2
Summary: 介绍
Home-page: UNKNOWN
Author: haoy_zhang
Author-email: 1278017087@qq.com
License: UNKNOWN
Platform: UNKNOWN
Classifier: Programming Language :: Python :: 3.6
Classifier: License :: OSI Approved :: MIT License
Classifier: Operating System :: OS Independent
Requires-Python: >=3.6
License-File: LICENSE.txt
Provides-Extra: cs20220112
Requires-Dist: python ; extra == 'cs20220112'
